{
  "annotations": {
    "list": [
      {
        "builtIn": 1,
        "datasource": {
          "type": "grafana",
          "uid": "-- Grafana --"
        },
        "enable": true,
        "hide": true,
        "iconColor": "rgba(0, 211, 255, 1)",
        "name": "Annotations & Alerts",
        "type": "dashboard"
      }
    ]
  },
  "description": "Grafana dashboard for 8401HR devices that are streaming to an InfluxDB2 data source",
  "editable": true,
  "fiscalYearStartMonth": 0,
  "graphTooltip": 0,
  "links": [],
  "panels": [
    {
      "datasource": {
        "type": "influxdb",
        "uid": "fepg8hwzyq9dsd"
      },
      "fieldConfig": {
        "defaults": {
          "color": {
            "mode": "palette-classic"
          },
          "custom": {
            "axisBorderShow": false,
            "axisCenteredZero": false,
            "axisColorMode": "text",
            "axisLabel": "",
            "axisPlacement": "auto",
            "barAlignment": 0,
            "barWidthFactor": 0.6,
            "drawStyle": "line",
            "fillOpacity": 0,
            "gradientMode": "none",
            "hideFrom": {
              "legend": false,
              "tooltip": false,
              "viz": false
            },
            "insertNulls": false,
            "lineInterpolation": "linear",
            "lineWidth": 1,
            "pointSize": 5,
            "scaleDistribution": {
              "type": "linear"
            },
            "showPoints": "auto",
            "spanNulls": false,
            "stacking": {
              "group": "A",
              "mode": "none"
            },
            "thresholdsStyle": {
              "mode": "off"
            }
          },
          "mappings": [],
          "thresholds": {
            "mode": "absolute",
            "steps": [
              {
                "color": "green"
              },
              {
                "color": "red",
                "value": 80
              }
            ]
          }
        },
        "overrides": []
      },
      "gridPos": {
        "h": 8,
        "w": 12,
        "x": 0,
        "y": 0
      },
      "id": 7,
      "maxDataPoints": 100000,
      "options": {
        "legend": {
          "calcs": [],
          "displayMode": "list",
          "placement": "bottom",
          "showLegend": true
        },
        "tooltip": {
          "hideZeros": false,
          "mode": "single",
          "sort": "none"
        }
      },
      "pluginVersion": "12.0.2",
      "targets": [
        {
          "query": "from(bucket: \"influx_dump\")\r\n  |> range(start: v.timeRangeStart, stop: v.timeRangeStop)\r\n  |> filter(fn: (r) =>\r\n      r._measurement == \"default-measurement\" and\r\n      r._field == \"value\" and\r\n      r.channel == \"TTL1\"\r\n  )  \r\n  |> yield(name: \"mean\")",
          "refId": "A"
        }
      ],
      "title": "TTL1",
      "type": "timeseries"
    },
    {
      "datasource": {
        "type": "influxdb",
        "uid": "fepg8hwzyq9dsd"
      },
      "fieldConfig": {
        "defaults": {
          "color": {
            "mode": "palette-classic"
          },
          "custom": {
            "axisBorderShow": false,
            "axisCenteredZero": false,
            "axisColorMode": "text",
            "axisLabel": "",
            "axisPlacement": "auto",
            "barAlignment": 0,
            "barWidthFactor": 0.6,
            "drawStyle": "line",
            "fillOpacity": 0,
            "gradientMode": "none",
            "hideFrom": {
              "legend": false,
              "tooltip": false,
              "viz": false
            },
            "insertNulls": false,
            "lineInterpolation": "linear",
            "lineWidth": 1,
            "pointSize": 5,
            "scaleDistribution": {
              "type": "linear"
            },
            "showPoints": "auto",
            "spanNulls": false,
            "stacking": {
              "group": "A",
              "mode": "none"
            },
            "thresholdsStyle": {
              "mode": "off"
            }
          },
          "mappings": [],
          "thresholds": {
            "mode": "absolute",
            "steps": [
              {
                "color": "green"
              },
              {
                "color": "red",
                "value": 80
              }
            ]
          }
        },
        "overrides": []
      },
      "gridPos": {
        "h": 8,
        "w": 12,
        "x": 12,
        "y": 0
      },
      "id": 8,
      "maxDataPoints": 100000,
      "options": {
        "legend": {
          "calcs": [],
          "displayMode": "list",
          "placement": "bottom",
          "showLegend": true
        },
        "tooltip": {
          "hideZeros": false,
          "mode": "single",
          "sort": "none"
        }
      },
      "pluginVersion": "12.0.2",
      "targets": [
        {
          "query": "from(bucket: \"influx_dump\")\r\n  |> range(start: v.timeRangeStart, stop: v.timeRangeStop)\r\n  |> filter(fn: (r) =>\r\n      r._measurement == \"default-measurement\" and\r\n      r._field == \"value\" and\r\n      r.channel == \"TTL2\"\r\n  )  \r\n  |> yield(name: \"mean\")",
          "refId": "A"
        }
      ],
      "title": "TTL2",
      "type": "timeseries"
    },
    {
      "datasource": {
        "type": "influxdb",
        "uid": "fepg8hwzyq9dsd"
      },
      "fieldConfig": {
        "defaults": {
          "color": {
            "mode": "palette-classic"
          },
          "custom": {
            "axisBorderShow": false,
            "axisCenteredZero": false,
            "axisColorMode": "text",
            "axisLabel": "",
            "axisPlacement": "auto",
            "barAlignment": 0,
            "barWidthFactor": 0.6,
            "drawStyle": "line",
            "fillOpacity": 0,
            "gradientMode": "none",
            "hideFrom": {
              "legend": false,
              "tooltip": false,
              "viz": false
            },
            "insertNulls": false,
            "lineInterpolation": "linear",
            "lineWidth": 1,
            "pointSize": 5,
            "scaleDistribution": {
              "type": "linear"
            },
            "showPoints": "auto",
            "spanNulls": false,
            "stacking": {
              "group": "A",
              "mode": "none"
            },
            "thresholdsStyle": {
              "mode": "off"
            }
          },
          "mappings": [],
          "thresholds": {
            "mode": "absolute",
            "steps": [
              {
                "color": "green"
              },
              {
                "color": "red",
                "value": 80
              }
            ]
          }
        },
        "overrides": []
      },
      "gridPos": {
        "h": 8,
        "w": 12,
        "x": 0,
        "y": 8
      },
      "id": 9,
      "maxDataPoints": 100000,
      "options": {
        "legend": {
          "calcs": [],
          "displayMode": "list",
          "placement": "bottom",
          "showLegend": true
        },
        "tooltip": {
          "hideZeros": false,
          "mode": "single",
          "sort": "none"
        }
      },
      "pluginVersion": "12.0.2",
      "targets": [
        {
          "query": "from(bucket: \"influx_dump\")\r\n  |> range(start: v.timeRangeStart, stop: v.timeRangeStop)\r\n  |> filter(fn: (r) =>\r\n      r._measurement == \"default-measurement\" and\r\n      r._field == \"value\" and\r\n      r.channel == \"TTL3\"\r\n  )  \r\n  |> yield(name: \"mean\")",
          "refId": "A"
        }
      ],
      "title": "TTL3",
      "type": "timeseries"
    },
    {
      "datasource": {
        "type": "influxdb",
        "uid": "fepg8hwzyq9dsd"
      },
      "fieldConfig": {
        "defaults": {
          "color": {
            "mode": "palette-classic"
          },
          "custom": {
            "axisBorderShow": false,
            "axisCenteredZero": false,
            "axisColorMode": "text",
            "axisLabel": "",
            "axisPlacement": "auto",
            "barAlignment": 0,
            "barWidthFactor": 0.6,
            "drawStyle": "line",
            "fillOpacity": 0,
            "gradientMode": "none",
            "hideFrom": {
              "legend": false,
              "tooltip": false,
              "viz": false
            },
            "insertNulls": false,
            "lineInterpolation": "linear",
            "lineWidth": 1,
            "pointSize": 5,
            "scaleDistribution": {
              "type": "linear"
            },
            "showPoints": "auto",
            "spanNulls": false,
            "stacking": {
              "group": "A",
              "mode": "none"
            },
            "thresholdsStyle": {
              "mode": "off"
            }
          },
          "mappings": [],
          "thresholds": {
            "mode": "absolute",
            "steps": [
              {
                "color": "green"
              },
              {
                "color": "red",
                "value": 80
              }
            ]
          }
        },
        "overrides": []
      },
      "gridPos": {
        "h": 8,
        "w": 12,
        "x": 12,
        "y": 8
      },
      "id": 10,
      "maxDataPoints": 100000,
      "options": {
        "legend": {
          "calcs": [],
          "displayMode": "list",
          "placement": "bottom",
          "showLegend": true
        },
        "tooltip": {
          "hideZeros": false,
          "mode": "single",
          "sort": "none"
        }
      },
      "pluginVersion": "12.0.2",
      "targets": [
        {
          "query": "from(bucket: \"influx_dump\")\r\n  |> range(start: v.timeRangeStart, stop: v.timeRangeStop)\r\n  |> filter(fn: (r) =>\r\n      r._measurement == \"default-measurement\" and\r\n      r._field == \"value\" and\r\n      r.channel == \"TTL4\"\r\n  )  \r\n  |> yield(name: \"mean\")",
          "refId": "A"
        }
      ],
      "title": "TTL4",
      "type": "timeseries"
    },
    {
      "datasource": {
        "type": "influxdb",
        "uid": "fepg8hwzyq9dsd"
      },
      "fieldConfig": {
        "defaults": {
          "color": {
            "mode": "palette-classic"
          },
          "custom": {
            "axisBorderShow": false,
            "axisCenteredZero": false,
            "axisColorMode": "text",
            "axisLabel": "",
            "axisPlacement": "auto",
            "barAlignment": 0,
            "barWidthFactor": 0.6,
            "drawStyle": "line",
            "fillOpacity": 0,
            "gradientMode": "none",
            "hideFrom": {
              "legend": false,
              "tooltip": false,
              "viz": false
            },
            "insertNulls": false,
            "lineInterpolation": "linear",
            "lineWidth": 1,
            "pointSize": 5,
            "scaleDistribution": {
              "type": "linear"
            },
            "showPoints": "auto",
            "spanNulls": false,
            "stacking": {
              "group": "A",
              "mode": "none"
            },
            "thresholdsStyle": {
              "mode": "off"
            }
          },
          "mappings": [],
          "thresholds": {
            "mode": "absolute",
            "steps": [
              {
                "color": "green"
              },
              {
                "color": "red",
                "value": 80
              }
            ]
          }
        },
        "overrides": []
      },
      "gridPos": {
        "h": 8,
        "w": 12,
        "x": 0,
        "y": 16
      },
      "id": 1,
      "maxDataPoints": 100000,
      "options": {
        "legend": {
          "calcs": [],
          "displayMode": "list",
          "placement": "bottom",
          "showLegend": true
        },
        "tooltip": {
          "hideZeros": false,
          "mode": "single",
          "sort": "none"
        }
      },
      "pluginVersion": "12.0.2",
      "targets": [
        {
          "datasource": {
            "type": "influxdb",
            "uid": "fepg8hwzyq9dsd"
          },
          "query": "from(bucket: \"influx_dump\")\r\n  |> range(start: v.timeRangeStart, stop: v.timeRangeStop)\r\n  |> filter(fn: (r) =>\r\n      r._measurement == \"default-measurement\" and\r\n      r._field == \"value\" and\r\n      r.channel == \"CHA\"\r\n  )   \r\n  |> aggregateWindow(every: 1ms, fn: mean)\r\n  |> yield(name: \"mean\")",
          "refId": "A"
        }
      ],
      "title": "CHA",
      "type": "timeseries"
    },
    {
      "datasource": {
        "type": "influxdb",
        "uid": "fepg8hwzyq9dsd"
      },
      "fieldConfig": {
        "defaults": {
          "color": {
            "mode": "palette-classic"
          },
          "custom": {
            "axisBorderShow": false,
            "axisCenteredZero": false,
            "axisColorMode": "text",
            "axisLabel": "",
            "axisPlacement": "auto",
            "barAlignment": 0,
            "barWidthFactor": 0.6,
            "drawStyle": "line",
            "fillOpacity": 0,
            "gradientMode": "none",
            "hideFrom": {
              "legend": false,
              "tooltip": false,
              "viz": false
            },
            "insertNulls": false,
            "lineInterpolation": "linear",
            "lineWidth": 1,
            "pointSize": 5,
            "scaleDistribution": {
              "type": "linear"
            },
            "showPoints": "auto",
            "spanNulls": false,
            "stacking": {
              "group": "A",
              "mode": "none"
            },
            "thresholdsStyle": {
              "mode": "off"
            }
          },
          "mappings": [],
          "thresholds": {
            "mode": "absolute",
            "steps": [
              {
                "color": "green"
              },
              {
                "color": "red",
                "value": 80
              }
            ]
          }
        },
        "overrides": []
      },
      "gridPos": {
        "h": 8,
        "w": 12,
        "x": 12,
        "y": 16
      },
      "id": 2,
      "maxDataPoints": 100000,
      "options": {
        "legend": {
          "calcs": [],
          "displayMode": "list",
          "placement": "bottom",
          "showLegend": true
        },
        "tooltip": {
          "hideZeros": false,
          "mode": "single",
          "sort": "none"
        }
      },
      "pluginVersion": "12.0.2",
      "targets": [
        {
          "query": "from(bucket: \"influx_dump\")\r\n  |> range(start: v.timeRangeStart, stop: v.timeRangeStop)\r\n  |> filter(fn: (r) =>\r\n      r._measurement == \"default-measurement\" and\r\n      r._field == \"value\" and\r\n      r.channel == \"CHB\"\r\n  )   \r\n  |> yield(name: \"mean\")",
          "refId": "A"
        }
      ],
      "title": "CHB",
      "type": "timeseries"
    },
    {
      "datasource": {
        "type": "influxdb",
        "uid": "fepg8hwzyq9dsd"
      },
      "fieldConfig": {
        "defaults": {
          "color": {
            "mode": "palette-classic"
          },
          "custom": {
            "axisBorderShow": false,
            "axisCenteredZero": false,
            "axisColorMode": "text",
            "axisLabel": "",
            "axisPlacement": "auto",
            "barAlignment": 0,
            "barWidthFactor": 0.6,
            "drawStyle": "line",
            "fillOpacity": 0,
            "gradientMode": "none",
            "hideFrom": {
              "legend": false,
              "tooltip": false,
              "viz": false
            },
            "insertNulls": false,
            "lineInterpolation": "linear",
            "lineWidth": 1,
            "pointSize": 5,
            "scaleDistribution": {
              "type": "linear"
            },
            "showPoints": "auto",
            "spanNulls": false,
            "stacking": {
              "group": "A",
              "mode": "none"
            },
            "thresholdsStyle": {
              "mode": "off"
            }
          },
          "mappings": [],
          "thresholds": {
            "mode": "absolute",
            "steps": [
              {
                "color": "green"
              },
              {
                "color": "red",
                "value": 80
              }
            ]
          }
        },
        "overrides": []
      },
      "gridPos": {
        "h": 8,
        "w": 12,
        "x": 0,
        "y": 24
      },
      "id": 3,
      "maxDataPoints": 100000,
      "options": {
        "legend": {
          "calcs": [],
          "displayMode": "list",
          "placement": "bottom",
          "showLegend": true
        },
        "tooltip": {
          "hideZeros": false,
          "mode": "single",
          "sort": "none"
        }
      },
      "pluginVersion": "12.0.2",
      "targets": [
        {
          "query": "from(bucket: \"influx_dump\")\r\n  |> range(start: v.timeRangeStart, stop: v.timeRangeStop)\r\n  |> filter(fn: (r) =>\r\n      r._measurement == \"default-measurement\" and\r\n      r._field == \"value\" and\r\n      r.channel == \"CHC\"\r\n  )   \r\n  |> yield(name: \"mean\")",
          "refId": "A"
        }
      ],
      "title": "CHC",
      "type": "timeseries"
    },
    {
      "datasource": {
        "type": "influxdb",
        "uid": "fepg8hwzyq9dsd"
      },
      "fieldConfig": {
        "defaults": {
          "color": {
            "mode": "palette-classic"
          },
          "custom": {
            "axisBorderShow": false,
            "axisCenteredZero": false,
            "axisColorMode": "text",
            "axisLabel": "",
            "axisPlacement": "auto",
            "barAlignment": 0,
            "barWidthFactor": 0.6,
            "drawStyle": "line",
            "fillOpacity": 0,
            "gradientMode": "none",
            "hideFrom": {
              "legend": false,
              "tooltip": false,
              "viz": false
            },
            "insertNulls": false,
            "lineInterpolation": "linear",
            "lineWidth": 1,
            "pointSize": 5,
            "scaleDistribution": {
              "type": "linear"
            },
            "showPoints": "auto",
            "spanNulls": false,
            "stacking": {
              "group": "A",
              "mode": "none"
            },
            "thresholdsStyle": {
              "mode": "off"
            }
          },
          "mappings": [],
          "thresholds": {
            "mode": "absolute",
            "steps": [
              {
                "color": "green"
              },
              {
                "color": "red",
                "value": 80
              }
            ]
          }
        },
        "overrides": []
      },
      "gridPos": {
        "h": 8,
        "w": 12,
        "x": 12,
        "y": 24
      },
      "id": 4,
      "maxDataPoints": 100000,
      "options": {
        "legend": {
          "calcs": [],
          "displayMode": "list",
          "placement": "bottom",
          "showLegend": true
        },
        "tooltip": {
          "hideZeros": false,
          "mode": "single",
          "sort": "none"
        }
      },
      "pluginVersion": "12.0.2",
      "targets": [
        {
          "query": "from(bucket: \"influx_dump\")\r\n  |> range(start: v.timeRangeStart, stop: v.timeRangeStop)\r\n  |> filter(fn: (r) =>\r\n      r._measurement == \"default-measurement\" and\r\n      r._field == \"value\" and\r\n      r.channel == \"CHD\"\r\n  )   \r\n  |> yield(name: \"mean\")",
          "refId": "A"
        }
      ],
      "title": "CHD",
      "type": "timeseries"
    },
    {
      "datasource": {
        "type": "influxdb",
        "uid": "fepg8hwzyq9dsd"
      },
      "fieldConfig": {
        "defaults": {
          "color": {
            "mode": "palette-classic"
          },
          "custom": {
            "axisBorderShow": false,
            "axisCenteredZero": false,
            "axisColorMode": "text",
            "axisLabel": "",
            "axisPlacement": "auto",
            "barAlignment": 0,
            "barWidthFactor": 0.6,
            "drawStyle": "line",
            "fillOpacity": 0,
            "gradientMode": "none",
            "hideFrom": {
              "legend": false,
              "tooltip": false,
              "viz": false
            },
            "insertNulls": false,
            "lineInterpolation": "linear",
            "lineWidth": 1,
            "pointSize": 5,
            "scaleDistribution": {
              "type": "linear"
            },
            "showPoints": "auto",
            "spanNulls": false,
            "stacking": {
              "group": "A",
              "mode": "none"
            },
            "thresholdsStyle": {
              "mode": "off"
            }
          },
          "mappings": [],
          "thresholds": {
            "mode": "absolute",
            "steps": [
              {
                "color": "green"
              },
              {
                "color": "red",
                "value": 80
              }
            ]
          }
        },
        "overrides": []
      },
      "gridPos": {
        "h": 8,
        "w": 12,
        "x": 0,
        "y": 32
      },
      "id": 5,
      "maxDataPoints": 100000,
      "options": {
        "legend": {
          "calcs": [],
          "displayMode": "list",
          "placement": "bottom",
          "showLegend": true
        },
        "tooltip": {
          "hideZeros": false,
          "mode": "single",
          "sort": "none"
        }
      },
      "pluginVersion": "12.0.2",
      "targets": [
        {
          "query": "from(bucket: \"influx_dump\")\r\n  |> range(start: v.timeRangeStart, stop: v.timeRangeStop)\r\n  |> filter(fn: (r) =>\r\n      r._measurement == \"default-measurement\" and\r\n      r._field == \"value\" and\r\n      r.channel == \"aEXT0\"\r\n  )  \r\n  |> yield(name: \"mean\")\r\n",
          "refId": "A"
        }
      ],
      "title": "aEXT0",
      "type": "timeseries"
    },
    {
      "datasource": {
        "type": "influxdb",
        "uid": "fepg8hwzyq9dsd"
      },
      "fieldConfig": {
        "defaults": {
          "color": {
            "mode": "palette-classic"
          },
          "custom": {
            "axisBorderShow": false,
            "axisCenteredZero": false,
            "axisColorMode": "text",
            "axisLabel": "",
            "axisPlacement": "auto",
            "barAlignment": 0,
            "barWidthFactor": 0.6,
            "drawStyle": "line",
            "fillOpacity": 0,
            "gradientMode": "none",
            "hideFrom": {
              "legend": false,
              "tooltip": false,
              "viz": false
            },
            "insertNulls": false,
            "lineInterpolation": "linear",
            "lineWidth": 1,
            "pointSize": 5,
            "scaleDistribution": {
              "type": "linear"
            },
            "showPoints": "auto",
            "spanNulls": false,
            "stacking": {
              "group": "A",
              "mode": "none"
            },
            "thresholdsStyle": {
              "mode": "off"
            }
          },
          "mappings": [],
          "thresholds": {
            "mode": "absolute",
            "steps": [
              {
                "color": "green"
              },
              {
                "color": "red",
                "value": 80
              }
            ]
          }
        },
        "overrides": []
      },
      "gridPos": {
        "h": 8,
        "w": 12,
        "x": 12,
        "y": 32
      },
      "id": 6,
      "maxDataPoints": 100000,
      "options": {
        "legend": {
          "calcs": [],
          "displayMode": "list",
          "placement": "bottom",
          "showLegend": true
        },
        "tooltip": {
          "hideZeros": false,
          "mode": "single",
          "sort": "none"
        }
      },
      "pluginVersion": "12.0.2",
      "targets": [
        {
          "query": "from(bucket: \"influx_dump\")\r\n  |> range(start: v.timeRangeStart, stop: v.timeRangeStop)\r\n  |> filter(fn: (r) =>\r\n      r._measurement == \"default-measurement\" and\r\n      r._field == \"value\" and\r\n      r.channel == \"aEXT1\"\r\n  )  \r\n  |> yield(name: \"mean\")",
          "refId": "A"
        }
      ],
      "title": "aEXT1",
      "type": "timeseries"
    }
  ],
  "preload": false,
  "refresh": "auto",
  "schemaVersion": 41,
  "tags": [],
  "templating": {
    "list": []
  },
  "time": {
    "from": "now-10s",
    "to": "now"
  },
  "timepicker": {},
  "timezone": "browser",
  "title": "8401_Template",
  "version": 9
}
