 [
    {
        "sentence_id": 1,
        "token_id": 1,
        "token": "Mwana",
        "lemma": "ana",
        "pos": "NOUN",
        "category_detail": "Mupanda 1",
        "morph_features": "NounClass=1|Rule=True",
        "tense": "",
        "aspect": "",
        "mood": "",
        "person": "",
        "number": "Singular",
        "gender": "N/A",
        "clitic_type": "",
        "dependency_relation": "nsubj",
        "gloss": "child",
        "comments": "Verified manually"
    },
    {
        "sentence_id": 2,
        "token_id": 1,
        "token": "Murimi",
        "lemma": "rimi",
        "pos": "NOUN",
        "category_detail": "Mupanda 1",
        "morph_features": "NounClass=1|Rule=True",
        "tense": "",
        "aspect": "",
        "mood": "",
        "person": "",
        "number": "Singular",
        "gender": "N/A",
        "clitic_type": "",
        "dependency_relation": "nsubj",
        "gloss": "farmer",
        "comments": "Verified manually"
    },
    {
        "sentence_id": 3,
        "token_id": 1,
        "token": "Mukuwasha",
        "lemma": "kwasha",
        "pos": "NOUN",
        "category_detail": "Mupanda 1",
        "morph_features": "NounClass=1|Rule=True",
        "tense": "",
        "aspect": "",
        "mood": "",
        "person": "",
        "number": "Singular",
        "gender": "male",
        "clitic_type": "",
        "dependency_relation": "nsubj",
        "gloss": "son-in-law",
        "comments": "Verified manually"
    },
    {
        "sentence_id": 4,
        "token_id": 1,
        "token": "Murora",
        "lemma": "rora",
        "pos": "NOUN",
        "category_detail": "Mupanda 1",
        "morph_features": "NounClass=1|Rule=True",
        "tense": "",
        "aspect": "",
        "mood": "",
        "person": "",
        "number": "Singular",
        "gender": "female",
        "clitic_type": "",
        "dependency_relation": "nsubj",
        "gloss": "daughter-in-law",
        "comments": "Verified manually"
    },
    {
        "sentence_id": 5,
        "token_id": 1,
        "token": "Mukoma",
        "lemma": "koma",
        "pos": "NOUN",
        "category_detail": "Mupanda 1",
        "morph_features": "NounClass=1|Rule=True",
        "tense": "",
        "aspect": "",
        "mood": "",
        "person": "",
        "number": "Singular",
        "gender": "N/A",
        "clitic_type": "",
        "dependency_relation": "nsubj",
        "gloss": "elder brother",
        "comments": "Verified manually"
    },
    {
        "sentence_id": 6,
        "token_id": 1,
        "token": "Munin'ina",
        "lemma": "n'ina",
        "pos": "NOUN",
        "category_detail": "Mupanda 1",
        "morph_features": "NounClass=1|Rule=True",
        "tense": "",
        "aspect": "",
        "mood": "",
        "person": "",
        "number": "Singular",
        "gender": "N/A",
        "clitic_type": "",
        "dependency_relation": "nsubj",
        "gloss": "younger sibling",
        "comments": "Verified manually"
    },
    {
        "sentence_id": 7,
        "token_id": 1,
        "token": "musikana",
        "lemma": "sikana",
        "pos": "NOUN",
        "category_detail": "Mupanda 1",
        "morph_features": "NounClass=1|Rule=True",
        "tense": "",
        "aspect": "",
        "mood": "",
        "person": "",
        "number": "Singular",
        "gender": "female",
        "clitic_type": "",
        "dependency_relation": "nsubj",
        "gloss": "girl",
        "comments": "Verified manually"
    },
    {
        "sentence_id": 8,
        "token_id": 1,
        "token": "Mukomana",
        "lemma": "komana",
        "pos": "NOUN",
        "category_detail": "Mupanda 1",
        "morph_features": "NounClass=1|Rule=True",
        "tense": "",
        "aspect": "",
        "mood": "",
        "person": "",
        "number": "Singular",
        "gender": "male",
        "clitic_type": "",
        "dependency_relation": "nsubj",
        "gloss": "boy",
        "comments": "Verified manually"
    },
    {
        "sentence_id": 9,
        "token_id": 1,
        "token": "Murume",
        "lemma": "rume",
        "pos": "NOUN",
        "category_detail": "Mupanda 1",
        "morph_features": "NounClass=1|Rule=True",
        "tense": "",
        "aspect": "",
        "mood": "",
        "person": "",
        "number": "Singular",
        "gender": "male",
        "clitic_type": "",
        "dependency_relation": "nsubj",
        "gloss": "man",
        "comments": "Verified manually"
    },
    {
        "sentence_id": 10,
        "token_id": 1,
        "token": "Mukadzi",
        "lemma": "kadzi",
        "pos": "NOUN",
        "category_detail": "Mupanda 1",
        "morph_features": "NounClass=1|Rule=True",
        "tense": "",
        "aspect": "",
        "mood": "",
        "person": "",
        "number": "Singular",
        "gender": "female",
        "clitic_type": "",
        "dependency_relation": "nsubj",
        "gloss": "woman",
        "comments": "Verified manually"
    },
    {
        "sentence_id": 34,
        "token_id": 1,
        "token": "Mupfumi",
        "lemma": "pfumi",
        "pos": "NOUN",
        "category_detail": "Mupanda 1",
        "morph_features": "NounClass=1|Attribute=Wealthy",
        "tense": "",
        "aspect": "",
        "mood": "",
        "person": "",
        "number": "Singular",
        "gender": "N/A",
        "clitic_type": "",
        "dependency_relation": "nsubj",
        "gloss": "rich person",
        "comments": "Verified manually"
    },
    {
        "sentence_id": 35,
        "token_id": 1,
        "token": "Murwere",
        "lemma": "rwere",
        "pos": "NOUN",
        "category_detail": "Mupanda 1",
        "morph_features": "NounClass=1|Rule=True",
        "tense": "",
        "aspect": "",
        "mood": "",
        "person": "",
        "number": "Singular",
        "gender": "N/A",
        "clitic_type": "",
        "dependency_relation": "nsubj",
        "gloss": "patient / sick person",
        "comments": "Verified manually"
    },
    {
        "sentence_id": 36,
        "token_id": 1,
        "token": "Mudzidzisi",
        "lemma": "dzidzisi",
        "pos": "NOUN",
        "category_detail": "Mupanda 1",
        "morph_features": "NounClass=1|Derivation=Agentive",
        "tense": "",
        "aspect": "",
        "mood": "",
        "person": "",
        "number": "Singular",
        "gender": "N/A",
        "clitic_type": "",
        "dependency_relation": "nsubj",
        "gloss": "teacher",
        "comments": "From kudzidzisa"
    },
    {
        "sentence_id": 37,
        "token_id": 1,
        "token": "Mubiki",
        "lemma": "bika",
        "pos": "NOUN",
        "category_detail": "Mupanda 1",
        "morph_features": "NounClass=1|Derivation=Agentive",
        "tense": "",
        "aspect": "",
        "mood": "",
        "person": "",
        "number": "Singular",
        "gender": "N/A",
        "clitic_type": "",
        "dependency_relation": "nsubj",
        "gloss": "cook",
        "comments": "From kubika"
    },
    {
        "sentence_id": 38,
        "token_id": 1,
        "token": "Murairidzi",
        "lemma": "raira",
        "pos": "NOUN",
        "category_detail": "Mupanda 1",
        "morph_features": "NounClass=1|Derivation=Agentive",
        "tense": "",
        "aspect": "",
        "mood": "",
        "person": "",
        "number": "Singular",
        "gender": "N/A",
        "clitic_type": "",
        "dependency_relation": "nsubj",
        "gloss": "instructor",
        "comments": "From kuraira"
    },
    {
        "sentence_id": 39,
        "token_id": 1,
        "token": "Murume mukuru",
        "lemma": "rume",
        "pos": "NOUN",
        "category_detail": "Mupanda 1",
        "morph_features": "NounClass=1|Compound=True",
        "tense": "",
        "aspect": "",
        "mood": "",
        "person": "",
        "number": "Singular",
        "gender": "male",
        "clitic_type": "",
        "dependency_relation": "nsubj",
        "gloss": "elder man",
        "comments": "Compound noun"
    },
    {
        "sentence_id": 40,
        "token_id": 1,
        "token": "Mupurisa",
        "lemma": "purisa",
        "pos": "NOUN",
        "category_detail": "Mupanda 1",
        "morph_features": "NounClass=1|Loanword=True",
        "tense": "",
        "aspect": "",
        "mood": "",
        "person": "",
        "number": "Singular",
        "gender": "N/A",
        "clitic_type": "",
        "dependency_relation": "nsubj",
        "gloss": "policeman",
        "comments": "From English 'police'"
    },
    {
        "sentence_id": 41,
        "token_id": 1,
        "token": "Muporofita",
        "lemma": "porofita",
        "pos": "NOUN",
        "category_detail": "Mupanda 1",
        "morph_features": "NounClass=1|Loanword=True",
        "tense": "",
        "aspect": "",
        "mood": "",
        "person": "",
        "number": "Singular",
        "gender": "N/A",
        "clitic_type": "",
        "dependency_relation": "nsubj",
        "gloss": "prophet",
        "comments": "Loanword"
    },
    {
        "sentence_id": 42,
        "token_id": 1,
        "token": "Mufundisi",
        "lemma": "fundisi",
        "pos": "NOUN",
        "category_detail": "Mupanda 1",
        "morph_features": "NounClass=1|Loanword=True",
        "tense": "",
        "aspect": "",
        "mood": "",
        "person": "",
        "number": "Singular",
        "gender": "male",
        "clitic_type": "",
        "dependency_relation": "nsubj",
        "gloss": "pastor",
        "comments": "Church title"
    },
    {
        "sentence_id": 100,
        "token_id": 1,
        "token": "vana",
        "lemma": "ana",
        "pos": "NOUN",
        "category_detail": "Mupanda 2",
        "morph_features": "NounClass=2|Rule=True",
        "tense": "",
        "aspect": "",
        "mood": "",
        "person": "",
        "number": "Plural",
        "gender": "N/A",
        "clitic_type": "",
        "dependency_relation": "nsubj",
        "gloss": "children",
        "comments": ""
    },
    {
        "sentence_id": 101,
        "token_id": 1,
        "token": "vakomana",
        "lemma": "komana",
        "pos": "NOUN",
        "category_detail": "Mupanda 2",
        "morph_features": "NounClass=2|Rule=True",
        "tense": "",
        "aspect": "",
        "mood": "",
        "person": "",
        "number": "Plural",
        "gender": "male",
        "clitic_type": "",
        "dependency_relation": "nsubj",
        "gloss": "boys",
        "comments": ""
    },
    {
        "sentence_id": 102,
        "token_id": 1,
        "token": "vasikana",
        "lemma": "sikana",
        "pos": "NOUN",
        "category_detail": "Mupanda 2",
        "morph_features": "NounClass=2|Rule=True",
        "tense": "",
        "aspect": "",
        "mood": "",
        "person": "",
        "number": "Plural",
        "gender": "female",
        "clitic_type": "",
        "dependency_relation": "nsubj",
        "gloss": "girls",
        "comments": ""
    },
    {
        "sentence_id": 103,
        "token_id": 1,
        "token": "varume",
        "lemma": "rume",
        "pos": "NOUN",
        "category_detail": "Mupanda 2",
        "morph_features": "NounClass=2|Rule=True",
        "tense": "",
        "aspect": "",
        "mood": "",
        "person": "",
        "number": "Plural",
        "gender": "male",
        "clitic_type": "",
        "dependency_relation": "nsubj",
        "gloss": "men",
        "comments": ""
    },
    {
        "sentence_id": 104,
        "token_id": 1,
        "token": "vakadzi",
        "lemma": "kadzi",
        "pos": "NOUN",
        "category_detail": "Mupanda 2",
        "morph_features": "NounClass=2|Rule=True",
        "tense": "",
        "aspect": "",
        "mood": "",
        "person": "",
        "number": "Plural",
        "gender": "female",
        "clitic_type": "",
        "dependency_relation": "nsubj",
        "gloss": "women",
        "comments": ""
    },
    {
        "sentence_id": 200,
        "token_id": 1,
        "token": "Vana",
        "lemma": "ana",
        "pos": "NOUN",
        "category_detail": "Mupanda 2",
        "morph_features": "NounClass=2|Rule=True",
        "tense": "",
        "aspect": "",
        "mood": "",
        "person": "",
        "number": "Plural",
        "gender": "N/A",
        "clitic_type": "",
        "dependency_relation": "nsubj",
        "gloss": "children",
        "comments": "Plural of Mwana"
    },
        {
        "sentence_id": 201,
        "token_id": 1,
        "token": "Vakomana",
        "lemma": "komana",
        "pos": "NOUN",
        "category_detail": "Mupanda 2",
        "morph_features": "NounClass=2|Rule=True",
        "tense": "",
        "aspect": "",
        "mood": "",
        "person": "",
        "number": "Plural",
        "gender": "male",
        "clitic_type": "",
        "dependency_relation": "nsubj",
        "gloss": "boys",
        "comments": "Plural of Mukomana"
    },
    {
        "sentence_id": 202,
        "token_id": 1,
        "token": "Vasikana",
        "lemma": "sikana",
        "pos": "NOUN",
        "category_detail": "Mupanda 2",
        "morph_features": "NounClass=2|Rule=True",
        "tense": "",
        "aspect": "",
        "mood": "",
        "person": "",
        "number": "Plural",
        "gender": "female",
        "clitic_type": "",
        "dependency_relation": "nsubj",
        "gloss": "girls",
        "comments": "Plural of Musikana"
    },
    {
        "sentence_id": 203,
        "token_id": 1,
        "token": "Varume",
        "lemma": "rume",
        "pos": "NOUN",
        "category_detail": "Mupanda 2",
        "morph_features": "NounClass=2|Rule=True",
        "tense": "",
        "aspect": "",
        "mood": "",
        "person": "",
        "number": "Plural",
        "gender": "male",
        "clitic_type": "",
        "dependency_relation": "nsubj",
        "gloss": "men",
        "comments": "Plural of Murume"
    },
    {
        "sentence_id": 204,
        "token_id": 1,
        "token": "Vakadzi",
        "lemma": "kadzi",
        "pos": "NOUN",
        "category_detail": "Mupanda 2",
        "morph_features": "NounClass=2|Rule=True",
        "tense": "",
        "aspect": "",
        "mood": "",
        "person": "",
        "number": "Plural",
        "gender": "female",
        "clitic_type": "",
        "dependency_relation": "nsubj",
        "gloss": "women",
        "comments": "Plural of Mukadzi"
    },
    {
        "sentence_id": 205,
        "token_id": 1,
        "token": "Vakwasha",
        "lemma": "kwasha",
        "pos": "NOUN",
        "category_detail": "Mupanda 2",
        "morph_features": "NounClass=2|Rule=True",
        "tense": "",
        "aspect": "",
        "mood": "",
        "person": "",
        "number": "Plural",
        "gender": "male",
        "clitic_type": "",
        "dependency_relation": "nsubj",
        "gloss": "sons-in-law",
        "comments": "Plural of Mukuwasha"
    },
    {
        "sentence_id": 206,
        "token_id": 1,
        "token": "Varoori",
        "lemma": "rora",
        "pos": "NOUN",
        "category_detail": "Mupanda 2",
        "morph_features": "NounClass=2|Rule=True",
        "tense": "",
        "aspect": "",
        "mood": "",
        "person": "",
        "number": "Plural",
        "gender": "female",
        "clitic_type": "",
        "dependency_relation": "nsubj",
        "gloss": "daughters-in-law",
        "comments": "Plural of Murora"
    },
    {
        "sentence_id": 207,
        "token_id": 1,
        "token": "Vabereki",
        "lemma": "bereki",
        "pos": "NOUN",
        "category_detail": "Mupanda 2",
        "morph_features": "NounClass=2|Rule=True",
        "tense": "",
        "aspect": "",
        "mood": "",
        "person": "",
        "number": "Plural",
        "gender": "N/A",
        "clitic_type": "",
        "dependency_relation": "nsubj",
        "gloss": "parents",
        "comments": "Plural of Mubereki"
    },
    {
        "sentence_id": 208,
        "token_id": 1,
        "token": "Vazukuru",
        "lemma": "zukuru",
        "pos": "NOUN",
        "category_detail": "Mupanda 2",
        "morph_features": "NounClass=2|Rule=True",
        "tense": "",
        "aspect": "",
        "mood": "",
        "person": "",
        "number": "Plural",
        "gender": "N/A",
        "clitic_type": "",
        "dependency_relation": "nsubj",
        "gloss": "nieces / nephews",
        "comments": "Plural of Muzukuru"
    },
    {
        "sentence_id": 209,
        "token_id": 1,
        "token": "Vadzimai",
        "lemma": "dzimai",
        "pos": "NOUN",
        "category_detail": "Mupanda 2",
        "morph_features": "NounClass=2|Rule=True",
        "tense": "",
        "aspect": "",
        "mood": "",
        "person": "",
        "number": "Plural",
        "gender": "female",
        "clitic_type": "",
        "dependency_relation": "nsubj",
        "gloss": "wives",
        "comments": "Plural of Mudzimai"
    },
    {
        "sentence_id": 210,
        "token_id": 1,
        "token": "Vafambi",
        "lemma": "famba",
        "pos": "NOUN",
        "category_detail": "Mupanda 2",
        "morph_features": "NounClass=2|Derivation=Agentive",
        "tense": "",
        "aspect": "",
        "mood": "",
        "person": "",
        "number": "Plural",
        "gender": "N/A",
        "clitic_type": "",
        "dependency_relation": "nsubj",
        "gloss": "travelers",
        "comments": "Plural of Mufambi"
    },
    {
        "sentence_id": 211,
        "token_id": 1,
        "token": "Vadzidzisi",
        "lemma": "dzidzisi",
        "pos": "NOUN",
        "category_detail": "Mupanda 2",
        "morph_features": "NounClass=2|Derivation=Agentive",
        "tense": "",
        "aspect": "",
        "mood": "",
        "person": "",
        "number": "Plural",
        "gender": "N/A",
        "clitic_type": "",
        "dependency_relation": "nsubj",
        "gloss": "teachers",
        "comments": "Plural of Mudzidzisi"
    },
    {
        "sentence_id": 212,
        "token_id": 1,
        "token": "Vapurisa",
        "lemma": "purisa",
        "pos": "NOUN",
        "category_detail": "Mupanda 2",
        "morph_features": "NounClass=2|Loanword=True",
        "tense": "",
        "aspect": "",
        "mood": "",
        "person": "",
        "number": "Plural",
        "gender": "N/A",
        "clitic_type": "",
        "dependency_relation": "nsubj",
        "gloss": "police officers",
        "comments": "Plural of Mupurisa"
    },
    {
        "sentence_id": 213,
        "token_id": 1,
        "token": "Vafundisi",
        "lemma": "fundisi",
        "pos": "NOUN",
        "category_detail": "Mupanda 2",
        "morph_features": "NounClass=2|Loanword=True",
        "tense": "",
        "aspect": "",
        "mood": "",
        "person": "",
        "number": "Plural",
        "gender": "male",
        "clitic_type": "",
        "dependency_relation": "nsubj",
        "gloss": "pastors",
        "comments": "Plural of Mufundisi"
    },
    {
        "sentence_id": 214,
        "token_id": 1,
        "token": "Vaporofita",
        "lemma": "porofita",
        "pos": "NOUN",
        "category_detail": "Mupanda 2",
        "morph_features": "NounClass=2|Loanword=True",
        "tense": "",
        "aspect": "",
        "mood": "",
        "person": "",
        "number": "Plural",
        "gender": "N/A",
        "clitic_type": "",
        "dependency_relation": "nsubj",
        "gloss": "prophets",
        "comments": "Plural of Muporofita"
    },
    {
        "sentence_id": 215,
        "token_id": 1,
        "token": "Vashandi",
        "lemma": "shanda",
        "pos": "NOUN",
        "category_detail": "Mupanda 2",
        "morph_features": "NounClass=2|Derivation=Agentive",
        "tense": "",
        "aspect": "",
        "mood": "",
        "person": "",
        "number": "Plural",
        "gender": "N/A",
        "clitic_type": "",
        "dependency_relation": "nsubj",
        "gloss": "workers",
        "comments": "Plural of Mushandi"
    },
    {
        "sentence_id": 216,
        "token_id": 1,
        "token": "Vadzimu",
        "lemma": "dzimu",
        "pos": "NOUN",
        "category_detail": "Mupanda 2",
        "morph_features": "NounClass=2|Spiritual=True",
        "tense": "",
        "aspect": "",
        "mood": "",
        "person": "",
        "number": "Plural",
        "gender": "N/A",
        "clitic_type": "",
        "dependency_relation": "nsubj",
        "gloss": "ancestral spirits",
        "comments": "Plural of Mudzimu"
    },
    {
        "sentence_id": 217,
        "token_id": 1,
        "token": "Vanyori",
        "lemma": "nyora",
        "pos": "NOUN",
        "category_detail": "Mupanda 2",
        "morph_features": "NounClass=2|Derivation=Agentive",
        "tense": "",
        "aspect": "",
        "mood": "",
        "person": "",
        "number": "Plural",
        "gender": "N/A",
        "clitic_type": "",
        "dependency_relation": "nsubj",
        "gloss": "writers",
        "comments": "Plural of Munyori"
    },
    {
        "sentence_id": 218,
        "token_id": 1,
        "token": "Vafemberi",
        "lemma": "fembera",
        "pos": "NOUN",
        "category_detail": "Mupanda 2",
        "morph_features": "NounClass=2|Derivation=Agentive",
        "tense": "",
        "aspect": "",
        "mood": "",
        "person": "",
        "number": "Plural",
        "gender": "N/A",
        "clitic_type": "",
        "dependency_relation": "nsubj",
        "gloss": "diviners",
        "comments": "Plural of Mufemberi"
    },
    {
        "sentence_id": 219,
        "token_id": 1,
        "token": "Vapfumi",
        "lemma": "pfumi",
        "pos": "NOUN",
        "category_detail": "Mupanda 2",
        "morph_features": "NounClass=2|Attribute=Wealthy",
        "tense": "",
        "aspect": "",
        "mood": "",
        "person": "",
        "number": "Plural",
        "gender": "N/A",
        "clitic_type": "",
        "dependency_relation": "nsubj",
        "gloss": "rich people",
        "comments": "Plural of Mupfumi"
    },
    {
        "sentence_id": 220,
        "token_id": 1,
        "token": "Vanhu",
        "lemma": "nhu",
        "pos": "NOUN",
        "category_detail": "Mupanda 2",
        "morph_features": "NounClass=2|Irregular=True",
        "tense": "",
        "aspect": "",
        "mood": "",
        "person": "",
        "number": "Plural",
        "gender": "N/A",
        "clitic_type": "",
        "dependency_relation": "nsubj",
        "gloss": "people / human beings",
        "comments": "Plural of Munhu"
    },
    {
        "sentence_id": 221,
        "token_id": 1,
        "token": "Vapenzi",
        "lemma": "penza",
        "pos": "NOUN",
        "category_detail": "Mupanda 2",
        "morph_features": "NounClass=2|Attribute=Foolish",
        "tense": "",
        "aspect": "",
        "mood": "",
        "person": "",
        "number": "Plural",
        "gender": "N/A",
        "clitic_type": "",
        "dependency_relation": "nsubj",
        "gloss": "fools / mad people",
        "comments": "Plural of Mupenzi"
    },
    {
        "sentence_id": 222,
        "token_id": 1,
        "token": "Varoyi",
        "lemma": "roya",
        "pos": "NOUN",
        "category_detail": "Mupanda 2",
        "morph_features": "NounClass=2|Cultural=True",
        "tense": "",
        "aspect": "",
        "mood": "",
        "person": "",
        "number": "Plural",
        "gender": "N/A",
        "clitic_type": "",
        "dependency_relation": "nsubj",
        "gloss": "witches / sorcerers",
        "comments": "Plural of Muroyi"
    },
    {
        "sentence_id": 223,
        "token_id": 1,
        "token": "Vanyepi",
        "lemma": "nyepa",
        "pos": "NOUN",
        "category_detail": "Mupanda 2",
        "morph_features": "NounClass=2|Attribute=Deceptive",
        "tense": "",
        "aspect": "",
        "mood": "",
        "person": "",
        "number": "Plural",
        "gender": "N/A",
        "clitic_type": "",
        "dependency_relation": "nsubj",
        "gloss": "liars",
        "comments": "Plural of Munyepi"
    },
    {
        "sentence_id": 224,
        "token_id": 1,
        "token": "Vashavi",
        "lemma": "shavi",
        "pos": "NOUN",
        "category_detail": "Mupanda 2",
        "morph_features": "NounClass=2|Spiritual=True",
        "tense": "",
        "aspect": "",
        "mood": "",
        "person": "",
        "number": "Plural",
        "gender": "N/A",
        "clitic_type": "",
        "dependency_relation": "nsubj",
        "gloss": "spirit mediums",
        "comments": "Plural of Mushavi"
    },
    {
        "sentence_id": 225,
        "token_id": 1,
        "token": "Vashumiri",
        "lemma": "shumira",
        "pos": "NOUN",
        "category_detail": "Mupanda 2",
        "morph_features": "NounClass=2|Religious=True",
        "tense": "",
        "aspect": "",
        "mood": "",
        "person": "",
        "number": "Plural",
        "gender": "N/A",
        "clitic_type": "",
        "dependency_relation": "nsubj",
        "gloss": "servants / ministers",
        "comments": "Plural of Mushumiri"
    },
    {
        "sentence_id": 226,
        "token_id": 1,
        "token": "Vabatsiri",
        "lemma": "batsira",
        "pos": "NOUN",
        "category_detail": "Mupanda 2",
        "morph_features": "NounClass=2|Derivation=Agentive",
        "tense": "",
        "aspect": "",
        "mood": "",
        "person": "",
        "number": "Plural",
        "gender": "N/A",
        "clitic_type": "",
        "dependency_relation": "nsubj",
        "gloss": "helpers / assistants",
        "comments": "Plural of Mubatsiri"
    },
    {
        "sentence_id": 227,
        "token_id": 1,
        "token": "Vagadziri",
        "lemma": "gadzira",
        "pos": "NOUN",
        "category_detail": "Mupanda 2",
        "morph_features": "NounClass=2|Derivation=Agentive",
        "tense": "",
        "aspect": "",
        "mood": "",
        "person": "",
        "number": "Plural",
        "gender": "N/A",
        "clitic_type": "",
        "dependency_relation": "nsubj",
        "gloss": "builders / creators",
        "comments": "Plural of Mugadziri"
    },
    {
        "sentence_id": 228,
        "token_id": 1,
        "token": "Vafudzi",
        "lemma": "fudza",
        "pos": "NOUN",
        "category_detail": "Mupanda 2",
        "morph_features": "NounClass=2|Derivation=Agentive",
        "tense": "",
        "aspect": "",
        "mood": "",
        "person": "",
        "number": "Plural",
        "gender": "N/A",
        "clitic_type": "",
        "dependency_relation": "nsubj",
        "gloss": "shepherds",
        "comments": "Plural of Mufudzi"
    },
    {
        "sentence_id": 229,
        "token_id": 1,
        "token": "Vabiki",
        "lemma": "bika",
        "pos": "NOUN",
        "category_detail": "Mupanda 2",
        "morph_features": "NounClass=2|Derivation=Agentive",
        "tense": "",
        "aspect": "",
        "mood": "",
        "person": "",
        "number": "Plural",
        "gender": "N/A",
        "clitic_type": "",
        "dependency_relation": "nsubj",
        "gloss": "cooks",
        "comments": "Plural of Mubiki"
    },
    {
        "sentence_id": 230,
        "token_id": 1,
        "token": "Vatambi",
        "lemma": "tamba",
        "pos": "NOUN",
        "category_detail": "Mupanda 2",
        "morph_features": "NounClass=2|Derivation=Agentive",
        "tense": "",
        "aspect": "",
        "mood": "",
        "person": "",
        "number": "Plural",
        "gender": "N/A",
        "clitic_type": "",
        "dependency_relation": "nsubj",
        "gloss": "players / dancers",
        "comments": "Plural of Mutambi"
    },
    {
        "sentence_id": 231,
        "token_id": 1,
        "token": "Vaperekedzi",
        "lemma": "perekedza",
        "pos": "NOUN",
        "category_detail": "Mupanda 2",
        "morph_features": "NounClass=2|Derivation=Agentive",
        "tense": "",
        "aspect": "",
        "mood": "",
        "person": "",
        "number": "Plural",
        "gender": "N/A",
        "clitic_type": "",
        "dependency_relation": "nsubj",
        "gloss": "escorts / companions",
        "comments": "Plural of Muperekedzi"
    },
    {
        "sentence_id": 232,
        "token_id": 1,
        "token": "Vashanyi",
        "lemma": "shanya",
        "pos": "NOUN",
        "category_detail": "Mupanda 2",
        "morph_features": "NounClass=2|Derivation=Agentive",
        "tense": "",
        "aspect": "",
        "mood": "",
        "person": "",
        "number": "Plural",
        "gender": "N/A",
        "clitic_type": "",
        "dependency_relation": "nsubj",
        "gloss": "visitors / tourists",
        "comments": "Plural of Mushanyi"
    },
    {
        "sentence_id": 233,
        "token_id": 1,
        "token": "Vagari",
        "lemma": "gara",
        "pos": "NOUN",
        "category_detail": "Mupanda 2",
        "morph_features": "NounClass=2|Derivation=Agentive",
        "tense": "",
        "aspect": "",
        "mood": "",
        "person": "",
        "number": "Plural",
        "gender": "N/A",
        "clitic_type": "",
        "dependency_relation": "nsubj",
        "gloss": "residents / dwellers",
        "comments": "Plural of Mugari"
    },
    {
        "sentence_id": 234,
        "token_id": 1,
        "token": "Vashambadzi",
        "lemma": "shambadza",
        "pos": "NOUN",
        "category_detail": "Mupanda 2",
        "morph_features": "NounClass=2|Derivation=Agentive",
        "tense": "",
        "aspect": "",
        "mood": "",
        "person": "",
        "number": "Plural",
        "gender": "N/A",
        "clitic_type": "",
        "dependency_relation": "nsubj",
        "gloss": "advertisers / broadcasters",
        "comments": "Plural of Mushambadzi"
    },
    {
        "sentence_id": 235,
        "token_id": 1,
        "token": "Vanyori venhau",
        "lemma": "nyora",
        "pos": "NOUN",
        "category_detail": "Mupanda 2",
        "morph_features": "NounClass=2|Compound=True",
        "tense": "",
        "aspect": "",
        "mood": "",
        "person": "",
        "number": "Plural",
        "gender": "N/A",
        "clitic_type": "",
        "dependency_relation": "nsubj",
        "gloss": "journalists / news writers",
        "comments": "Plural of Munyori wenhau"
    },
    {
        "sentence_id": 236,
        "token_id": 1,
        "token": "Vanyori vemabhuku",
        "lemma": "nyora",
        "pos": "NOUN",
        "category_detail": "Mupanda 2",
        "morph_features": "NounClass=2|Compound=True",
        "tense": "",
        "aspect": "",
        "mood": "",
        "person": "",
        "number": "Plural",
        "gender": "N/A",
        "clitic_type": "",
        "dependency_relation": "nsubj",
        "gloss": "book authors",
        "comments": "Plural of Munyori wemabhuku"
    },
    {
        "sentence_id": 1212,
        "token_id": 1,
        "token": "Kuchikoro",
        "lemma": "chikoro",
        "pos": "NOUN",
        "category_detail": "Mupanda 17",
        "morph_features": "NounClass=17|Prefix=ku-|Locative=True|Directional=True|Educational=True",
        "tense": "",
        "aspect": "",
        "mood": "",
        "person": "",
        "number": "Singular",
        "gender": "N/A",
        "clitic_type": "",
        "dependency_relation": "obl",
        "gloss": "to school",
        "comments": "Educational destination"
    },
    {
        "sentence_id": 1213,
        "token_id": 1,
        "token": "Kumabvazuva",
        "lemma": "mabvazuva",
        "pos": "NOUN",
        "category_detail": "Mupanda 17",
        "morph_features": "NounClass=17|Prefix=ku-|Locative=True|Directional=True|Geographic=True",
        "tense": "",
        "aspect": "",
        "mood": "",
        "person": "",
        "number": "Singular",
        "gender": "N/A",
        "clitic_type": "",
        "dependency_relation": "obl",
        "gloss": "to the east",
        "comments": "Directional geography"
    },
    {
        "sentence_id": 1214,
        "token_id": 1,
        "token": "Kumadokero",
        "lemma": "madokero",
        "pos": "NOUN",
        "category_detail": "Mupanda 17",
        "morph_features": "NounClass=17|Prefix=ku-|Locative=True|Directional=True|Geographic=True",
        "tense": "",
        "aspect": "",
        "mood": "",
        "person": "",
        "number": "Singular",
        "gender": "N/A",
        "clitic_type": "",
        "dependency_relation": "obl",
        "gloss": "to the west",
        "comments": "Opposite of Kumabvazuva"
    },
    {
        "sentence_id": 1215,
        "token_id": 1,
        "token": "Kumunda",
        "lemma": "munda",
        "pos": "NOUN",
        "category_detail": "Mupanda 17",
        "morph_features": "NounClass=17|Prefix=ku-|Locative=True|Directional=True|Agricultural=True",
        "tense": "",
        "aspect": "",
        "mood": "",
        "person": "",
        "number": "Singular",
        "gender": "N/A",
        "clitic_type": "",
        "dependency_relation": "obl",
        "gloss": "to the field",
        "comments": "Agricultural direction"
    },
    {
        "sentence_id": 1216,
        "token_id": 1,
        "token": "Kunevamwe",
        "lemma": "vamwe",
        "pos": "NOUN",
        "category_detail": "Mupanda 17",
        "morph_features": "NounClass=17|Prefix=ku-|Locative=True|Directional=True|Human=True",
        "tense": "",
        "aspect": "",
        "mood": "",
        "person": "",
        "number": "Singular",
        "gender": "N/A",
        "clitic_type": "",
        "dependency_relation": "obl",
        "gloss": "towards others / to people",
        "comments": "Human-directed motion"
    },
    {
        "sentence_id": 1217,
        "token_id": 1,
        "token": "Kumakomo",
        "lemma": "makomo",
        "pos": "NOUN",
        "category_detail": "Mupanda 17",
        "morph_features": "NounClass=17|Prefix=ku-|Locative=True|Directional=True|Geographic=True",
        "tense": "",
        "aspect": "",
        "mood": "",
        "person": "",
        "number": "Singular",
        "gender": "N/A",
        "clitic_type": "",
        "dependency_relation": "obl",
        "gloss": "to the mountains",
        "comments": "Geographic direction"
    },
    {
        "sentence_id": 1218,
        "token_id": 1,
        "token": "Kundiro",
        "lemma": "ndiro",
        "pos": "NOUN",
        "category_detail": "Mupanda 17",
        "morph_features": "NounClass=17|Prefix=ku-|Locative=True|Directional=True|Object=True",
        "tense": "",
        "aspect": "",
        "mood": "",
        "person": "",
        "number": "Singular",
        "gender": "N/A",
        "clitic_type": "",
        "dependency_relation": "obl",
        "gloss": "to the plate",
        "comments": "Object-directed location"
    },
    {
        "sentence_id": 1230,
        "token_id": 1,
        "token": "Mumusha",
        "lemma": "musha",
        "pos": "NOUN",
        "category_detail": "Mupanda 18",
        "morph_features": "NounClass=18|Prefix=mu-|Locative=True|Internal=True|Home=True",
        "tense": "",
        "aspect": "",
        "mood": "",
        "person": "",
        "number": "Singular",
        "gender": "N/A",
        "clitic_type": "",
        "dependency_relation": "obl",
        "gloss": "in the homestead / within the village",
        "comments": "Common locative"
    },
    {
        "sentence_id": 1231,
        "token_id": 1,
        "token": "Muguta",
        "lemma": "guta",
        "pos": "NOUN",
        "category_detail": "Mupanda 18",
        "morph_features": "NounClass=18|Prefix=mu-|Locative=True|Internal=True|Urban=True",
        "tense": "",
        "aspect": "",
        "mood": "",
        "person": "",
        "number": "Singular",
        "gender": "N/A",
        "clitic_type": "",
        "dependency_relation": "obl",
        "gloss": "in the city",
        "comments": "Urban locative"
    },
    {
        "sentence_id": 1232,
        "token_id": 1,
        "token": "Mumunda",
        "lemma": "munda",
        "pos": "NOUN",
        "category_detail": "Mupanda 18",
        "morph_features": "NounClass=18|Prefix=mu-|Locative=True|Internal=True|Agricultural=True",
        "tense": "",
        "aspect": "",
        "mood": "",
        "person": "",
        "number": "Singular",
        "gender": "N/A",
        "clitic_type": "",
        "dependency_relation": "obl",
        "gloss": "in the field",
        "comments": "Agricultural context"
    },
    {
        "sentence_id": 1233,
        "token_id": 1,
        "token": "Muchikoro",
        "lemma": "chikoro",
        "pos": "NOUN",
        "category_detail": "Mupanda 18",
        "morph_features": "NounClass=18|Prefix=mu-|Locative=True|Internal=True|Educational=True",
        "tense": "",
        "aspect": "",
        "mood": "",
        "person": "",
        "number": "Singular",
        "gender": "N/A",
        "clitic_type": "",
        "dependency_relation": "obl",
        "gloss": "inside the school",
        "comments": "Educational space"
    },
    {
        "sentence_id": 1234,
        "token_id": 1,
        "token": "Mumba",
        "lemma": "imba",
        "pos": "NOUN",
        "category_detail": "Mupanda 18",
        "morph_features": "NounClass=18|Prefix=mu-|Locative=True|Internal=True|Domestic=True",
        "tense": "",
        "aspect": "",
        "mood": "",
        "person": "",
        "number": "Singular",
        "gender": "N/A",
        "clitic_type": "",
        "dependency_relation": "obl",
        "gloss": "inside the house",
        "comments": "Household context"
    },
    {
        "sentence_id": 1235,
        "token_id": 1,
        "token": "Murwizi",
        "lemma": "rwizi",
        "pos": "NOUN",
        "category_detail": "Mupanda 18",
        "morph_features": "NounClass=18|Prefix=mu-|Locative=True|Internal=True|Natural=True",
        "tense": "",
        "aspect": "",
        "mood": "",
        "person": "",
        "number": "Singular",
        "gender": "N/A",
        "clitic_type": "",
        "dependency_relation": "obl",
        "gloss": "in the river",
        "comments": "Natural context"
    },
    {
        "sentence_id": 1236,
        "token_id": 1,
        "token": "Mumapako",
        "lemma": "mapako",
        "pos": "NOUN",
        "category_detail": "Mupanda 18",
        "morph_features": "NounClass=18|Prefix=mu-|Locative=True|Internal=True|Geographic=True|Plural=True",
        "tense": "",
        "aspect": "",
        "mood": "",
        "person": "",
        "number": "Singular",
        "gender": "N/A",
        "clitic_type": "",
        "dependency_relation": "obl",
        "gloss": "in the caves",
        "comments": "Geographic plural"
    },
    {
        "sentence_id": 1237,
        "token_id": 1,
        "token": "Mukati",
        "lemma": "kati",
        "pos": "NOUN",
        "category_detail": "Mupanda 18",
        "morph_features": "NounClass=18|Prefix=mu-|Locative=True|Internal=True|Relational=True",
        "tense": "",
        "aspect": "",
        "mood": "",
        "person": "",
        "number": "Singular",
        "gender": "N/A",
        "clitic_type": "",
        "dependency_relation": "obl",
        "gloss": "inside / within",
        "comments": "General relational term"
    },
    {
        "sentence_id": 1238,
        "token_id": 1,
        "token": "Mumhanza",
        "lemma": "mhanza",
        "pos": "NOUN",
        "category_detail": "Mupanda 18",
        "morph_features": "NounClass=18|Prefix=mu-|Locative=True|Internal=True|BodyPart=True",
        "tense": "",
        "aspect": "",
        "mood": "",
        "person": "",
        "number": "Singular",
        "gender": "N/A",
        "clitic_type": "",
        "dependency_relation": "obl",
        "gloss": "on/in the forehead",
        "comments": "Body part locative"
    },
    {
        "sentence_id": 1239,
        "token_id": 1,
        "token": "Mupfungwa",
        "lemma": "pfungwa",
        "pos": "NOUN",
        "category_detail": "Mupanda 18",
        "morph_features": "NounClass=18|Prefix=mu-|Locative=True|Internal=True|Cognitive=True",
        "tense": "",
        "aspect": "",
        "mood": "",
        "person": "",
        "number": "Singular",
        "gender": "N/A",
        "clitic_type": "",
        "dependency_relation": "obl",
        "gloss": "in the mind",
        "comments": "Abstract locative expression"
    },
    {
        "sentence_id": 1300,
        "token_id": 1,
        "token": "Pfungwa",
        "lemma": "pfungwa",
        "pos": "NOUN",
        "category_detail": "Mupanda 19",
        "morph_features": "NounClass=19|Abstract=True|Cognitive=True",
        "tense": "",
        "aspect": "",
        "mood": "",
        "person": "",
        "number": "Singular",
        "gender": "N/A",
        "clitic_type": "",
        "dependency_relation": "nsubj",
        "gloss": "thought / idea",
        "comments": "Abstract cognitive noun"
    },
    {
        "sentence_id": 1301,
        "token_id": 1,
        "token": "Pfumo",
        "lemma": "pfumo",
        "pos": "NOUN",
        "category_detail": "Mupanda 19",
        "morph_features": "NounClass=19|Object=True|Weapon=True",
        "tense": "",
        "aspect": "",
        "mood": "",
        "person": "",
        "number": "Singular",
        "gender": "N/A",
        "clitic_type": "",
        "dependency_relation": "nsubj",
        "gloss": "spear",
        "comments": "Archaic noun, relic class 19/5 hybrid"
    },
    {
        "sentence_id": 1302,
        "token_id": 1,
        "token": "Pfupi",
        "lemma": "pfupi",
        "pos": "ADJ",
        "category_detail": "Mupanda 19",
        "morph_features": "NounClass=19|AdjForm=True|Size=True",
        "tense": "",
        "aspect": "",
        "mood": "",
        "person": "",
        "number": "Singular",
        "gender": "N/A",
        "clitic_type": "",
        "dependency_relation": "amod",
        "gloss": "short",
        "comments": "Qualitative adjective used as class marker"
    },
    {
        "sentence_id": 1303,
        "token_id": 1,
        "token": "Pfi",
        "lemma": "pfi",
        "pos": "IDEOPH",
        "category_detail": "Mupanda 19",
        "morph_features": "NounClass=19|Ideophone=True|Sound=True",
        "tense": "",
        "aspect": "",
        "mood": "",
        "person": "",
        "number": "Singular",
        "gender": "N/A",
        "clitic_type": "",
        "dependency_relation": "discourse",
        "gloss": "(sound of something falling sharply)",
        "comments": "Onomatopoeic class 19 form"
    },
    {
        "sentence_id": 1304,
        "token_id": 1,
        "token": "Pfira",
        "lemma": "pfira",
        "pos": "VERB",
        "category_detail": "Mupanda 19",
        "morph_features": "NounClass=19|VerbDerived=True|Action=True",
        "tense": "",
        "aspect": "",
        "mood": "",
        "person": "",
        "number": "Singular",
        "gender": "N/A",
        "clitic_type": "",
        "dependency_relation": "root",
        "gloss": "to pour / to offer libation",
        "comments": "Derived from ideophone root"
    },
    {
        "sentence_id": 1305,
        "token_id": 1,
        "token": "Pfupi-pfupi",
        "lemma": "pfupi",
        "pos": "ADJ",
        "category_detail": "Mupanda 19",
        "morph_features": "NounClass=19|Reduplicated=True|Adjectival=True",
        "tense": "",
        "aspect": "",
        "mood": "",
        "person": "",
        "number": "Singular",
        "gender": "N/A",
        "clitic_type": "",
        "dependency_relation": "amod",
        "gloss": "very short / compact",
        "comments": "Intensified adjective"
    },
    {
        "sentence_id": 1306,
        "token_id": 1,
        "token": "Pfumbamwe",
        "lemma": "pfumbamwe",
        "pos": "NUM",
        "category_detail": "Mupanda 19",
        "morph_features": "NounClass=19|Numeric=True",
        "tense": "",
        "aspect": "",
        "mood": "",
        "person": "",
        "number": "Singular",
        "gender": "N/A",
        "clitic_type": "",
        "dependency_relation": "nummod",
        "gloss": "nine",
        "comments": "Numeral historically linked to class 19 prefix"
    },
    {
        "sentence_id": 1307,
        "token_id": 1,
        "token": "Pfuma",
        "lemma": "pfuma",
        "pos": "NOUN",
        "category_detail": "Mupanda 19",
        "morph_features": "NounClass=19|Abstract=True|Wealth=True",
        "tense": "",
        "aspect": "",
        "mood": "",
        "person": "",
        "number": "Singular",
        "gender": "N/A",
        "clitic_type": "",
        "dependency_relation": "nsubj",
        "gloss": "wealth / riches",
        "comments": "Classical Bantu class 19 abstract noun"
    },
    {
        "sentence_id": 1308,
        "token_id": 1,
        "token": "Pfambi",
        "lemma": "pfambi",
        "pos": "NOUN",
        "category_detail": "Mupanda 19",
        "morph_features": "NounClass=19|Human=True|Social=True|Stigmatic=True",
        "tense": "",
        "aspect": "",
        "mood": "",
        "person": "",
        "number": "Singular",
        "gender": "female",
        "clitic_type": "",
        "dependency_relation": "nsubj",
        "gloss": "prostitute / unfaithful woman",
        "comments": "Social noun, archaic root"
    },
    {
        "sentence_id": 1309,
        "token_id": 1,
        "token": "Pfupiwo",
        "lemma": "pfupi",
        "pos": "ADV",
        "category_detail": "Mupanda 19",
        "morph_features": "NounClass=19|Adverbial=True|Modifier=True",
        "tense": "",
        "aspect": "",
        "mood": "",
        "person": "",
        "number": "Singular",
        "gender": "N/A",
        "clitic_type": "",
        "dependency_relation": "advmod",
        "gloss": "also short / likewise short",
        "comments": "Adverbial use of adjective root"
    },
    {
        "sentence_id": 1400,
        "token_id": 1,
        "token": "Kufamba",
        "lemma": "famba",
        "pos": "NOUN",
        "category_detail": "Mupanda 20",
        "morph_features": "NounClass=20|Prefix=ku-|Nominalized=True|Action=True",
        "tense": "",
        "aspect": "",
        "mood": "",
        "person": "",
        "number": "Singular",
        "gender": "N/A",
        "clitic_type": "",
        "dependency_relation": "nsubj",
        "gloss": "walking / journey",
        "comments": "Abstract action noun"
    },
    {
        "sentence_id": 1401,
        "token_id": 1,
        "token": "Kudzidza",
        "lemma": "dzidza",
        "pos": "NOUN",
        "category_detail": "Mupanda 20",
        "morph_features": "NounClass=20|Prefix=ku-|Nominalized=True|Education=True",
        "tense": "",
        "aspect": "",
        "mood": "",
        "person": "",
        "number": "Singular",
        "gender": "N/A",
        "clitic_type": "",
        "dependency_relation": "nsubj",
        "gloss": "learning / education",
        "comments": "Abstract educational noun"
    },
    {
        "sentence_id": 1402,
        "token_id": 1,
        "token": "Kushanda",
        "lemma": "shanda",
        "pos": "NOUN",
        "category_detail": "Mupanda 20",
        "morph_features": "NounClass=20|Prefix=ku-|Nominalized=True|Work=True",
        "tense": "",
        "aspect": "",
        "mood": "",
        "person": "",
        "number": "Singular",
        "gender": "N/A",
        "clitic_type": "",
        "dependency_relation": "nsubj",
        "gloss": "work / labour",
        "comments": "Derived from verb 'to work'"
    },
    {
        "sentence_id": 1403,
        "token_id": 1,
        "token": "Kufunga",
        "lemma": "funga",
        "pos": "NOUN",
        "category_detail": "Mupanda 20",
        "morph_features": "NounClass=20|Prefix=ku-|Nominalized=True|Cognitive=True",
        "tense": "",
        "aspect": "",
        "mood": "",
        "person": "",
        "number": "Singular",
        "gender": "N/A",
        "clitic_type": "",
        "dependency_relation": "nsubj",
        "gloss": "thought / thinking",
        "comments": "Cognitive abstract"
    },
    {
        "sentence_id": 1404,
        "token_id": 1,
        "token": "Kuda",
        "lemma": "da",
        "pos": "NOUN",
        "category_detail": "Mupanda 20",
        "morph_features": "NounClass=20|Prefix=ku-|Nominalized=True|Emotional=True",
        "tense": "",
        "aspect": "",
        "mood": "",
        "person": "",
        "number": "Singular",
        "gender": "N/A",
        "clitic_type": "",
        "dependency_relation": "nsubj",
        "gloss": "love / affection / desire",
        "comments": "Emotive abstraction"
    },
    {
        "sentence_id": 1405,
        "token_id": 1,
        "token": "Kutya",
        "lemma": "tya",
        "pos": "NOUN",
        "category_detail": "Mupanda 20",
        "morph_features": "NounClass=20|Prefix=ku-|Nominalized=True|Emotion=True|Negative=True",
        "tense": "",
        "aspect": "",
        "mood": "",
        "person": "",
        "number": "Singular",
        "gender": "N/A",
        "clitic_type": "",
        "dependency_relation": "nsubj",
        "gloss": "fear",
        "comments": "Emotive abstraction"
    },
    {
        "sentence_id": 1406,
        "token_id": 1,
        "token": "Kushushikana",
        "lemma": "shushikana",
        "pos": "NOUN",
        "category_detail": "Mupanda 20",
        "morph_features": "NounClass=20|Prefix=ku-|Nominalized=True|Psychological=True",
        "tense": "",
        "aspect": "",
        "mood": "",
        "person": "",
        "number": "Singular",
        "gender": "N/A",
        "clitic_type": "",
        "dependency_relation": "nsubj",
        "gloss": "worry / anxiety",
        "comments": "Derived from stative verb"
    },
    {
        "sentence_id": 1407,
        "token_id": 1,
        "token": "Kurima",
        "lemma": "rima",
        "pos": "NOUN",
        "category_detail": "Mupanda 20",
        "morph_features": "NounClass=20|Prefix=ku-|Nominalized=True|Agricultural=True",
        "tense": "",
        "aspect": "",
        "mood": "",
        "person": "",
        "number": "Singular",
        "gender": "N/A",
        "clitic_type": "",
        "dependency_relation": "nsubj",
        "gloss": "farming",
        "comments": "Agricultural activity noun"
    },
    {
        "sentence_id": 1408,
        "token_id": 1,
        "token": "Kugara",
        "lemma": "gara",
        "pos": "NOUN",
        "category_detail": "Mupanda 20",
        "morph_features": "NounClass=20|Prefix=ku-|Nominalized=True|Habitual=True",
        "tense": "",
        "aspect": "",
        "mood": "",
        "person": "",
        "number": "Singular",
        "gender": "N/A",
        "clitic_type": "",
        "dependency_relation": "nsubj",
        "gloss": "residence / way of living",
        "comments": "Derived from state verb"
    },
    {
        "sentence_id": 1409,
        "token_id": 1,
        "token": "Kuzvarwa",
        "lemma": "zvarwa",
        "pos": "NOUN",
        "category_detail": "Mupanda 20",
        "morph_features": "NounClass=20|Prefix=ku-|Nominalized=True|Event=True",
        "tense": "",
        "aspect": "",
        "mood": "",
        "person": "",
        "number": "Singular",
        "gender": "N/A",
        "clitic_type": "",
        "dependency_relation": "nsubj",
        "gloss": "birth",
        "comments": "Event nominalization"
    },
    {
        "sentence_id": 1420,
        "token_id": 1,
        "token": "Kamwana",
        "lemma": "mwana",
        "pos": "NOUN",
        "category_detail": "Diminutive",
        "morph_features": "Prefix=ka-|Small=True|Affection=True|Singular=True",
        "tense": "",
        "aspect": "",
        "mood": "",
        "person": "",
        "number": "Singular",
        "gender": "N/A",
        "clitic_type": "",
        "dependency_relation": "nsubj",
        "gloss": "small child",
        "comments": "Diminutive derived from 'mwana'"
    },
    {
        "sentence_id": 1421,
        "token_id": 1,
        "token": "Tuvana",
        "lemma": "vana",
        "pos": "NOUN",
        "category_detail": "DiminutivePlural",
        "morph_features": "Prefix=tu-|Small=True|Plural=True",
        "tense": "",
        "aspect": "",
        "mood": "",
        "person": "",
        "number": "Plural",
        "gender": "N/A",
        "clitic_type": "",
        "dependency_relation": "nsubj",
        "gloss": "small children",
        "comments": "Plural diminutive of 'kamwana'"
    },
    {
        "sentence_id": 1422,
        "token_id": 1,
        "token": "Kamukadzi",
        "lemma": "mukadzi",
        "pos": "NOUN",
        "category_detail": "Diminutive",
        "morph_features": "Prefix=ka-|Small=True|PejorativePossible=True",
        "tense": "",
        "aspect": "",
        "mood": "",
        "person": "",
        "number": "Singular",
        "gender": "female",
        "clitic_type": "",
        "dependency_relation": "nsubj",
        "gloss": "small/insignificant woman",
        "comments": "Diminutive with social nuance"
    },
    {
        "sentence_id": 1423,
        "token_id": 1,
        "token": "Kamusha",
        "lemma": "musha",
        "pos": "NOUN",
        "category_detail": "Diminutive",
        "morph_features": "Prefix=ka-|Small=True|Locative=True",
        "tense": "",
        "aspect": "",
        "mood": "",
        "person": "",
        "number": "Singular",
        "gender": "N/A",
        "clitic_type": "",
        "dependency_relation": "nsubj",
        "gloss": "small village",
        "comments": "Locative diminutive"
    },
    {
        "sentence_id": 1430,
        "token_id": 1,
        "token": "Zimoto",
        "lemma": "moto",
        "pos": "NOUN",
        "category_detail": "Augmentative",
        "morph_features": "Prefix=zi-|Large=True|Intense=True",
        "tense": "",
        "aspect": "",
        "mood": "",
        "person": "",
        "number": "Singular",
        "gender": "N/A",
        "clitic_type": "",
        "dependency_relation": "nsubj",
        "gloss": "big fire",
        "comments": "Augmentative form"
    },
    {
        "sentence_id": 1431,
        "token_id": 1,
        "token": "Gombarume",
        "lemma": "murume",
        "pos": "NOUN",
        "category_detail": "Augmentative",
        "morph_features": "Prefix=gomba-|Intensified=True|Masculine=True",
        "tense": "",
        "aspect": "",
        "mood": "",
        "person": "",
        "number": "Singular",
        "gender": "male",
        "clitic_type": "",
        "dependency_relation": "nsubj",
        "gloss": "strong/big man",
        "comments": "Common augmentative noun"
    },
    {
        "sentence_id": 1432,
        "token_id": 1,
        "token": "Zvino",
        "lemma": "zvino",
        "pos": "ADV",
        "category_detail": "AugmentativeForm",
        "morph_features": "Prefix=zi-|Temporal=True",
        "tense": "",
        "aspect": "",
        "mood": "",
        "person": "",
        "number": "Singular",
        "gender": "N/A",
        "clitic_type": "",
        "dependency_relation": "advmod",
        "gloss": "now (literally: at this large moment)",
        "comments": "Semantic augmentative shift"
    },
    {
        "sentence_id": 1433,
        "token_id": 1,
        "token": "Zvitunha",
        "lemma": "tunha",
        "pos": "NOUN",
        "category_detail": "AugmentativePlural",
        "morph_features": "Prefix=zvi-|Large=True|Plural=True|Negative=True",
        "tense": "",
        "aspect": "",
        "mood": "",
        "person": "",
        "number": "Plural",
        "gender": "N/A",
        "clitic_type": "",
        "dependency_relation": "nsubj",
        "gloss": "big corpses / carcasses",
        "comments": "Negative augmentative plural"
    },
    {
        "sentence_id": 1500,
        "token_id": 1,
        "token": "Ini",
        "lemma": "ini",
        "pos": "PRON",
        "category_detail": "Independent",
        "morph_features": "Person=1|Number=Singular|Independent=True",
        "tense": "",
        "aspect": "",
        "mood": "",
        "person": "1",
        "number": "Singular",
        "gender": "N/A",
        "clitic_type": "",
        "dependency_relation": "nsubj",
        "gloss": "I / me",
        "comments": "1st person singular subject"
    },
    {
        "sentence_id": 1501,
        "token_id": 1,
        "token": "Iwe",
        "lemma": "iwe",
        "pos": "PRON",
        "category_detail": "Independent",
        "morph_features": "Person=2|Number=Singular|Independent=True",
        "tense": "",
        "aspect": "",
        "mood": "",
        "person": "2",
        "number": "Singular",
        "gender": "N/A",
        "clitic_type": "",
        "dependency_relation": "nsubj",
        "gloss": "you (singular)",
        "comments": "2nd person singular"
    },
    {
        "sentence_id": 1502,
        "token_id": 1,
        "token": "Iye",
        "lemma": "iye",
        "pos": "PRON",
        "category_detail": "Independent",
        "morph_features": "Person=3|Number=Singular|Independent=True|Gender=Neutral",
        "tense": "",
        "aspect": "",
        "mood": "",
        "person": "3",
        "number": "Singular",
        "gender": "N/A",
        "clitic_type": "",
        "dependency_relation": "nsubj",
        "gloss": "he / she",
        "comments": "3rd person singular"
    },
    {
        "sentence_id": 1503,
        "token_id": 1,
        "token": "Isu",
        "lemma": "isu",
        "pos": "PRON",
        "category_detail": "Independent",
        "morph_features": "Person=1|Number=Plural|Independent=True",
        "tense": "",
        "aspect": "",
        "mood": "",
        "person": "1",
        "number": "Plural",
        "gender": "N/A",
        "clitic_type": "",
        "dependency_relation": "nsubj",
        "gloss": "we / us",
        "comments": "1st person plural"
    },
    {
        "sentence_id": 1504,
        "token_id": 1,
        "token": "Imi",
        "lemma": "imi",
        "pos": "PRON",
        "category_detail": "Independent",
        "morph_features": "Person=2|Number=Plural|Independent=True|Respect=True",
        "tense": "",
        "aspect": "",
        "mood": "",
        "person": "2",
        "number": "Plural",
        "gender": "N/A",
        "clitic_type": "",
        "dependency_relation": "nsubj",
        "gloss": "you (plural or respectful singular)",
        "comments": "Used for politeness"
    },
    {
        "sentence_id": 1505,
        "token_id": 1,
        "token": "Ivo",
        "lemma": "ivo",
        "pos": "PRON",
        "category_detail": "Independent",
        "morph_features": "Person=3|Number=Plural|Independent=True",
        "tense": "",
        "aspect": "",
        "mood": "",
        "person": "3",
        "number": "Plural",
        "gender": "N/A",
        "clitic_type": "",
        "dependency_relation": "nsubj",
        "gloss": "they / them",
        "comments": "3rd person plural"
    },
    {
        "sentence_id": 1510,
        "token_id": 1,
        "token": "Wangu",
        "lemma": "angu",
        "pos": "PRON",
        "category_detail": "Possessive",
        "morph_features": "Person=1|Number=Singular|Agreement=NounClass1",
        "tense": "",
        "aspect": "",
        "mood": "",
        "person": "1",
        "number": "Singular",
        "gender": "N/A",
        "clitic_type": "",
        "dependency_relation": "nmod:poss",
        "gloss": "mine (singular)",
        "comments": "Used with class 1 nouns"
    },
    {
        "sentence_id": 1511,
        "token_id": 1,
        "token": "Wako",
        "lemma": "ako",
        "pos": "PRON",
        "category_detail": "Possessive",
        "morph_features": "Person=2|Number=Singular|Agreement=NounClass1",
        "tense": "",
        "aspect": "",
        "mood": "",
        "person": "2",
        "number": "Singular",
        "gender": "N/A",
        "clitic_type": "",
        "dependency_relation": "nmod:poss",
        "gloss": "yours (singular)",
        "comments": "Possessor 2SG"
    },
    {
        "sentence_id": 1512,
        "token_id": 1,
        "token": "Wake",
        "lemma": "ake",
        "pos": "PRON",
        "category_detail": "Possessive",
        "morph_features": "Person=3|Number=Singular|Agreement=NounClass1",
        "tense": "",
        "aspect": "",
        "mood": "",
        "person": "3",
        "number": "Singular",
        "gender": "N/A",
        "clitic_type": "",
        "dependency_relation": "nmod:poss",
        "gloss": "his / hers",
        "comments": "3rd person singular"
    },
    {
        "sentence_id": 1513,
        "token_id": 1,
        "token": "Wedu",
        "lemma": "edu",
        "pos": "PRON",
        "category_detail": "Possessive",
        "morph_features": "Person=1|Number=Plural|Agreement=NounClass2",
        "tense": "",
        "aspect": "",
        "mood": "",
        "person": "1",
        "number": "Plural",
        "gender": "N/A",
        "clitic_type": "",
        "dependency_relation": "nmod:poss",
        "gloss": "ours",
        "comments": "Possessor 1PL"
    },
    {
        "sentence_id": 1514,
        "token_id": 1,
        "token": "Wenyu",
        "lemma": "enyu",
        "pos": "PRON",
        "category_detail": "Possessive",
        "morph_features": "Person=2|Number=Plural|Agreement=NounClass2",
        "tense": "",
        "aspect": "",
        "mood": "",
        "person": "2",
        "number": "Plural",
        "gender": "N/A",
        "clitic_type": "",
        "dependency_relation": "nmod:poss",
        "gloss": "yours (plural)",
        "comments": "Possessor 2PL"
    },
    {
        "sentence_id": 1515,
        "token_id": 1,
        "token": "Wavo",
        "lemma": "avo",
        "pos": "PRON",
        "category_detail": "Possessive",
        "morph_features": "Person=3|Number=Plural|Agreement=NounClass2",
        "tense": "",
        "aspect": "",
        "mood": "",
        "person": "3",
        "number": "Plural",
        "gender": "N/A",
        "clitic_type": "",
        "dependency_relation": "nmod:poss",
        "gloss": "theirs",
        "comments": "3rd person plural"
    },
    {
        "sentence_id": 1520,
        "token_id": 1,
        "token": "ndi",
        "lemma": "ndi",
        "pos": "PRON",
        "category_detail": "ObjectPrefix",
        "morph_features": "Person=1|Number=Singular|Clitic=True",
        "tense": "",
        "aspect": "",
        "mood": "",
        "person": "1",
        "number": "Singular",
        "gender": "N/A",
        "clitic_type": "object",
        "dependency_relation": "obj",
        "gloss": "me",
        "comments": "1SG object marker"
    },
    {
        "sentence_id": 1521,
        "token_id": 1,
        "token": "ku",
        "lemma": "ku",
        "pos": "PRON",
        "category_detail": "ObjectPrefix",
        "morph_features": "Person=2|Number=Singular|Clitic=True",
        "tense": "",
        "aspect": "",
        "mood": "",
        "person": "2",
        "number": "Singular",
        "gender": "N/A",
        "clitic_type": "object",
        "dependency_relation": "obj",
        "gloss": "you",
        "comments": "2SG object marker"
    },
    {
        "sentence_id": 1522,
        "token_id": 1,
        "token": "mu",
        "lemma": "mu",
        "pos": "PRON",
        "category_detail": "ObjectPrefix",
        "morph_features": "Person=3|Number=Singular|Clitic=True",
        "tense": "",
        "aspect": "",
        "mood": "",
        "person": "3",
        "number": "Singular",
        "gender": "N/A",
        "clitic_type": "object",
        "dependency_relation": "obj",
        "gloss": "him/her",
        "comments": "3SG object marker"
    },
    {
        "sentence_id": 1523,
        "token_id": 1,
        "token": "ti",
        "lemma": "ti",
        "pos": "PRON",
        "category_detail": "ObjectPrefix",
        "morph_features": "Person=1|Number=Plural|Clitic=True",
        "tense": "",
        "aspect": "",
        "mood": "",
        "person": "1",
        "number": "Plural",
        "gender": "N/A",
        "clitic_type": "object",
        "dependency_relation": "obj",
        "gloss": "us",
        "comments": "1PL object marker"
    },
    {
        "sentence_id": 1524,
        "token_id": 1,
        "token": "mi",
        "lemma": "mi",
        "pos": "PRON",
        "category_detail": "ObjectPrefix",
        "morph_features": "Person=2|Number=Plural|Clitic=True",
        "tense": "",
        "aspect": "",
        "mood": "",
        "person": "2",
        "number": "Plural",
        "gender": "N/A",
        "clitic_type": "object",
        "dependency_relation": "obj",
        "gloss": "you (plural)",
        "comments": "2PL object marker"
    },
    {
        "sentence_id": 1525,
        "token_id": 1,
        "token": "va",
        "lemma": "va",
        "pos": "PRON",
        "category_detail": "ObjectPrefix",
        "morph_features": "Person=3|Number=Plural|Clitic=True",
        "tense": "",
        "aspect": "",
        "mood": "",
        "person": "3",
        "number": "Plural",
        "gender": "N/A",
        "clitic_type": "object",
        "dependency_relation": "obj",
        "gloss": "them",
        "comments": "3PL object marker"
    },
    {
        "sentence_id": 1530,
        "token_id": 1,
        "token": "zvi",
        "lemma": "zvi",
        "pos": "PRON",
        "category_detail": "Reflexive",
        "morph_features": "Person=3|Number=PluralOrSingular|Reflexive=True|Clitic=True",
        "tense": "",
        "aspect": "",
        "mood": "",
        "person": "",
        "number": "",
        "gender": "N/A",
        "clitic_type": "reflexive",
        "dependency_relation": "expl",
        "gloss": "oneself / themselves",
        "comments": "Universal reflexive clitic"
    },
    {
        "sentence_id": 1531,
        "token_id": 1,
        "token": "ndi",
        "lemma": "ndi",
        "pos": "PRON",
        "category_detail": "ReflexiveVariant",
        "morph_features": "Person=1|Number=Singular|Reflexive=True|Clitic=True",
        "tense": "",
        "aspect": "",
        "mood": "",
        "person": "1",
        "number": "Singular",
        "gender": "N/A",
        "clitic_type": "reflexive",
        "dependency_relation": "expl",
        "gloss": "myself",
        "comments": "Used in some dialects or emphasis"
    },
    {
        "sentence_id": 1532,
        "token_id": 1,
        "token": "dzi",
        "lemma": "dzi",
        "pos": "PRON",
        "category_detail": "ReflexiveVariant",
        "morph_features": "Person=2|Number=Singular|Reflexive=True|Dialectal=True",
        "tense": "",
        "aspect": "",
        "mood": "",
        "person": "2",
        "number": "Singular",
        "gender": "N/A",
        "clitic_type": "reflexive",
        "dependency_relation": "expl",
        "gloss": "yourself",
        "comments": "Less common, dialectal reflexive marker"
    },
    {
        "sentence_id": 1540,
        "token_id": 1,
        "token": "Uyu",
        "lemma": "uyu",
        "pos": "PRON",
        "category_detail": "Demonstrative",
        "morph_features": "NounClass=1|Proximity=Near|Deictic=True",
        "tense": "",
        "aspect": "",
        "mood": "",
        "person": "",
        "number": "Singular",
        "gender": "N/A",
        "clitic_type": "",
        "dependency_relation": "nsubj",
        "gloss": "this (person)",
        "comments": "Proximal demonstrative"
    },
    {
        "sentence_id": 1541,
        "token_id": 1,
        "token": "Uyo",
        "lemma": "uyo",
        "pos": "PRON",
        "category_detail": "Demonstrative",
        "morph_features": "NounClass=1|Proximity=Far|Deictic=True",
        "tense": "",
        "aspect": "",
        "mood": "",
        "person": "",
        "number": "Singular",
        "gender": "N/A",
        "clitic_type": "",
        "dependency_relation": "nsubj",
        "gloss": "that (person)",
        "comments": "Distal demonstrative"
    },
    {
        "sentence_id": 1542,
        "token_id": 1,
        "token": "Ichi",
        "lemma": "ichi",
        "pos": "PRON",
        "category_detail": "Demonstrative",
        "morph_features": "NounClass=7|Proximity=Near|Deictic=True",
        "tense": "",
        "aspect": "",
        "mood": "",
        "person": "",
        "number": "Singular",
        "gender": "N/A",
        "clitic_type": "",
        "dependency_relation": "nsubj",
        "gloss": "this (thing)",
        "comments": "Class 7 proximal"
    },
    {
        "sentence_id": 1543,
        "token_id": 1,
        "token": "Icho",
        "lemma": "icho",
        "pos": "PRON",
        "category_detail": "Demonstrative",
        "morph_features": "NounClass=7|Proximity=Far|Deictic=True",
        "tense": "",
        "aspect": "",
        "mood": "",
        "person": "",
        "number": "Singular",
        "gender": "N/A",
        "clitic_type": "",
        "dependency_relation": "nsubj",
        "gloss": "that (thing)",
        "comments": "Class 7 distal"
    },
    {
        "sentence_id": 1544,
        "token_id": 1,
        "token": "Iyi",
        "lemma": "iyi",
        "pos": "PRON",
        "category_detail": "Demonstrative",
        "morph_features": "NounClass=9|Proximity=Near|Deictic=True",
        "tense": "",
        "aspect": "",
        "mood": "",
        "person": "",
        "number": "Singular",
        "gender": "N/A",
        "clitic_type": "",
        "dependency_relation": "nsubj",
        "gloss": "this (feminine noun class)",
        "comments": "Class 9 proximal"
    },
    {
        "sentence_id": 1545,
        "token_id": 1,
        "token": "Iyo",
        "lemma": "iyo",
        "pos": "PRON",
        "category_detail": "Demonstrative",
        "morph_features": "NounClass=9|Proximity=Far|Deictic=True",
        "tense": "",
        "aspect": "",
        "mood": "",
        "person": "",
        "number": "Singular",
        "gender": "N/A",
        "clitic_type": "",
        "dependency_relation": "nsubj",
        "gloss": "that (feminine noun class)",
        "comments": "Class 9 distal"
    },
    {
        "sentence_id": 1546,
        "token_id": 1,
        "token": "Ivo ava",
        "lemma": "ava",
        "pos": "PRON",
        "category_detail": "DemonstrativePlural",
        "morph_features": "NounClass=2|Proximity=Near|Number=Plural",
        "tense": "",
        "aspect": "",
        "mood": "",
        "person": "",
        "number": "Plural",
        "gender": "N/A",
        "clitic_type": "",
        "dependency_relation": "nsubj",
        "gloss": "these (people)",
        "comments": "Plural demonstrative for class 2"
    },
    {
        "sentence_id": 1547,
        "token_id": 1,
        "token": "Ivo avo",
        "lemma": "avo",
        "pos": "PRON",
        "category_detail": "DemonstrativePlural",
        "morph_features": "NounClass=2|Proximity=Far|Number=Plural",
        "tense": "",
        "aspect": "",
        "mood": "",
        "person": "",
        "number": "Plural",
        "gender": "N/A",
        "clitic_type": "",
        "dependency_relation": "nsubj",
        "gloss": "those (people)",
        "comments": "Plural demonstrative for class 2"
    },
    {
        "sentence_id": 1550,
        "token_id": 1,
        "token": "Ano",
        "lemma": "no",
        "pos": "PRON",
        "category_detail": "Relative",
        "morph_features": "NounClass=1|Relative=True|VerbAgreement=True",
        "tense": "",
        "aspect": "",
        "mood": "",
        "person": "",
        "number": "Singular",
        "gender": "N/A",
        "clitic_type": ""
    }
]